dataset/filters.json
dataset/json_schema.json
lighting_filters/__init__.py
lighting_filters/lighting_filters.py
lighting_filters/typedef.py
lighting_filters-0.1.1.dist-info/LICENSE
lighting_filters-0.1.1.dist-info/METADATA
lighting_filters-0.1.1.dist-info/WHEEL
lighting_filters-0.1.1.dist-info/RECORD
