Metadata-Version: 2.1
Name: lighting_filters
Version: 0.1.1
Summary: A collection of data relating to lighting color filters
License: MIT
Author: Reid Sox-Harris
Author-email: reid@soxharris.com
Requires-Python: >=3.9,<4.0
Classifier: License :: OSI Approved :: MIT License
Classifier: Programming Language :: Python :: 3
Classifier: Programming Language :: Python :: 3.9
Classifier: Programming Language :: Python :: 3.10
Classifier: Programming Language :: Python :: 3.11
Classifier: Programming Language :: Python :: 3.12
Classifier: Programming Language :: Python :: 3.13
Requires-Dist: pydantic (>=2.10.4,<3.0.0)
